pytatsu/__init__.py
pytatsu/__main__.py
pytatsu/tss.py
pytatsu-0.1.5.dist-info/entry_points.txt
pytatsu-0.1.5.dist-info/LICENSE
pytatsu-0.1.5.dist-info/WHEEL
pytatsu-0.1.5.dist-info/METADATA
pytatsu-0.1.5.dist-info/RECORD
