Metadata-Version: 2.1
Name: pytatsu
Version: 0.1.5
Summary: A Python library/CLI tool for requesting and saving SHSH blobs from Apple's Tatsu signing server API.
Home-page: https://github.com/Cryptiiiic/pytatsu
License: LGPL-3.0-only
Author: Cryptiiiic
Author-email: liamwqs@gmail.com
Requires-Python: >=3.10,<4.0
Classifier: License :: OSI Approved :: GNU Lesser General Public License v3 (LGPLv3)
Classifier: Programming Language :: Python :: 3
Classifier: Programming Language :: Python :: 3.10
Classifier: Programming Language :: Python :: 3.11
Requires-Dist: aiohttp (>=3.8.3,<4.0.0)
Requires-Dist: pybmtool (>=0.1.4,<0.2.0)
Project-URL: Bug Tracker, https://github.com/Cryptiiiic/pytatsu/issues
Project-URL: Repository, https://github.com/Cryptiiiic/pytatsu
